dkbotzpro/__init__.py
dkbotzpro/api.py
dkbotzpro-1.1.1.dist-info/licenses/LICENSE
dkbotzpro-1.1.1.dist-info/METADATA
dkbotzpro-1.1.1.dist-info/WHEEL
dkbotzpro-1.1.1.dist-info/top_level.txt
dkbotzpro-1.1.1.dist-info/RECORD
