Metadata-Version: 2.4
Name: dkbotzpro
Version: 1.1.1
Summary: A DKBotzPro is a Python package that helps Many things This is Free API
Home-page: https://github.com/DKBOTZPROJECT/DKBOTZPRO
Author: DKBOTZ
License: GNU AFFERO GENERAL PUBLIC LICENSE (v3)
Classifier: Programming Language :: Python :: 3
Classifier: Programming Language :: Python :: 3.6
Classifier: Programming Language :: Python :: 3.7
Classifier: Programming Language :: Python :: 3.8
Classifier: Programming Language :: Python :: 3.9
Classifier: License :: OSI Approved :: GNU General Public License v3 (GPLv3)
Classifier: Operating System :: OS Independent
Requires-Python: >=3.6
License-File: LICENSE
Requires-Dist: requests
Dynamic: author
Dynamic: classifier
Dynamic: description
Dynamic: description-content-type
Dynamic: home-page
Dynamic: license
Dynamic: license-file
Dynamic: requires-dist
Dynamic: requires-python
Dynamic: summary
